dbnd_dbt_monitor/__init__.py
dbnd_dbt_monitor/data/__init__.py
dbnd_dbt_monitor/data/dbt_config_data.py
dbnd_dbt_monitor/fetcher/__init__.py
dbnd_dbt_monitor/fetcher/dbt_cloud_data_fetcher.py
dbnd_dbt_monitor/multiserver/__init__.py
dbnd_dbt_monitor/multiserver/dbt_multiserver.py
dbnd_dbt_monitor/multiserver/dbt_services_factory.py
dbnd_dbt_monitor/syncer/__init__.py
dbnd_dbt_monitor/syncer/dbt_runs_syncer.py
dbnd_dbt_monitor/tracking_service/__init__.py
dbnd_dbt_monitor/tracking_service/dbt_syncer_management_service.py
dbnd_dbt_monitor/tracking_service/dbt_tracking_service.py
dbnd_dbt_monitor-1.0.12.18.dist-info/LICENSE
dbnd_dbt_monitor-1.0.12.18.dist-info/METADATA
dbnd_dbt_monitor-1.0.12.18.dist-info/WHEEL
dbnd_dbt_monitor-1.0.12.18.dist-info/entry_points.txt
dbnd_dbt_monitor-1.0.12.18.dist-info/top_level.txt
dbnd_dbt_monitor-1.0.12.18.dist-info/RECORD
