Metadata-Version: 2.1
Name: dbnd-dbt-monitor
Version: 1.0.12.18
Summary: Machine Learning Orchestration
Home-page: https://github.com/databand-ai/dbnd
Author: Evgeny Shulman
Author-email: evgeny.shulman@databand.ai
Maintainer: Evgeny Shulman
Maintainer-email: evgeny.shulman@databand.ai
Project-URL: Documentation, https://dbnd.readme.io/
Project-URL: Bug-Tracker, https://github.com/databand-ai/dbnd/issues
Project-URL: Source-Code, https://github.com/databand-ai/dbnd
Keywords: orchestration,data,machinelearning
Platform: any
Classifier: Development Status :: 4 - Beta
Classifier: Intended Audience :: Developers
Classifier: Natural Language :: English
Classifier: License :: OSI Approved :: Apache Software License
Classifier: Operating System :: OS Independent
Classifier: Programming Language :: Python
Classifier: Programming Language :: Python :: 3
Classifier: Programming Language :: Python :: 3.7
Classifier: Programming Language :: Python :: 3.8
Classifier: Programming Language :: Python :: 3.9
Classifier: Programming Language :: Python :: 3.10
Classifier: Programming Language :: Python :: Implementation :: CPython
Classifier: Programming Language :: Python :: Implementation :: PyPy
Classifier: Topic :: Software Development :: Libraries :: Python Modules
License-File: LICENSE
Requires-Dist: dbnd (==1.0.12.18)
Requires-Dist: dbnd-airflow-monitor (==1.0.12.18)
Requires-Dist: requests (>=2.25.0)
Requires-Dist: python-json-logger
Requires-Dist: sentry-sdk
Provides-Extra: tests
Requires-Dist: pytest ; extra == 'tests'
Requires-Dist: mock ; extra == 'tests'
